{
  "updated": "2026-07-13T21:12:46Z",
  "version": "V4.8",
  "status": "BLOQUEADO",
  "headline": "BOT-ARQ en modo BLOQUEADO. Mercado NEUTRO.",
  "summary": {
    "mercado": "NEUTRO",
    "estado_operativo": "BLOQUEADO",
    "capital_total_estimado_usd": 5834.3,
    "ganancia_total_estimada_usd": 834.3,
    "operaciones_abiertas": 0,
    "exposicion_abierta_pct": 0.0,
    "riesgo_abierto_pct": 0.0,
    "drawdown_pct": 27.55,
    "backtest_win_rate_pct": 33.67,
    "backtest_profit_factor": 1.14,
    "backtest_operaciones": 300
  },
  "top_opportunities": [
    {
      "ticker": "ANET",
      "sector": "Redes / IA",
      "senal_bot": "BUY",
      "score": 81.6,
      "riesgo": "BAJO",
      "rr": 1.63,
      "precio": 181.15,
      "objetivo": 205.0
    },
    {
      "ticker": "ABNB",
      "sector": "Viajes",
      "senal_bot": "BUY",
      "score": 78.9,
      "riesgo": "BAJO",
      "rr": 1.63,
      "precio": 146.33,
      "objetivo": 156.89
    },
    {
      "ticker": "WMB",
      "sector": "Energía",
      "senal_bot": "BUY",
      "score": 78.0,
      "riesgo": "BAJO",
      "rr": 1.63,
      "precio": 74.46,
      "objetivo": 78.98
    },
    {
      "ticker": "NU",
      "sector": "Fintech",
      "senal_bot": "BUY",
      "score": 77.9,
      "riesgo": "BAJO",
      "rr": 1.63,
      "precio": 13.67,
      "objetivo": 14.76
    },
    {
      "ticker": "AXP",
      "sector": "Pagos",
      "senal_bot": "BUY",
      "score": 77.1,
      "riesgo": "BAJO",
      "rr": 1.63,
      "precio": 354.43,
      "objetivo": 373.66
    }
  ],
  "open_positions": [],
  "alerts": [
    "Estado operativo BLOQUEADO: Volumen relativo bajo",
    "Diagnóstico general marca riesgo ALTO.",
    "Reglas operativas V4.4 en estado BLOQUEADO."
  ],
  "conclusion": "No abrir nuevas posiciones hasta que bajen riesgo, exposicion o drawdown. Mantener seguimiento de cartera abierta.",
  "recommendations": [
    "Revisar primero estado operativo y limites de exposicion/riesgo.",
    "Usar Top oportunidades como lista de vigilancia, no como orden real.",
    "Validar tickers omitidos antes de interpretar ausencia de senales."
  ],
  "nota": "Reporte ejecutivo automatico para paper trading simulado. No es asesoria financiera."
}