{
  "updated": "17-07-2026 12:53 PM Colombia",
  "version": "V4.4.4",
  "mode": "AUDITORIA_BLOQUEOS_EXISTENTES",
  "summary": {
    "blocked_count": 50,
    "buy_candidates_count": 62,
    "open_positions_count": 0,
    "warnings_count": 2,
    "main_block_reason": "Volumen relativo bajo"
  },
  "warnings": [
    "Diagnóstico general marca riesgo ALTO.",
    "Reglas operativas V4.4 en estado BLOQUEADO."
  ],
  "block_reasons": [
    {
      "reason": "Volumen relativo bajo",
      "count": 47
    },
    {
      "reason": "Bloqueo operativo por drawdown máximo: 27.55%",
      "count": 3
    }
  ],
  "blocked_signals": [
    {
      "id": "BLOCK-1",
      "date": "2026-07-17",
      "ticker": "OKE",
      "signal": "BUY",
      "reason": "Volumen relativo bajo",
      "risk": "BAJO",
      "rr": 1.63,
      "score": 77.6,
      "price": 93.02,
      "exposure_pct": 0.0,
      "open_risk_pct": 0.0,
      "drawdown_pct": 27.55,
      "operational_rule": false,
      "decision": "BLOCKED_BY_EXISTING_RULE"
    },
    {
      "id": "BLOCK-2",
      "date": "2026-07-17",
      "ticker": "EOG",
      "signal": "BUY",
      "reason": "Volumen relativo bajo",
      "risk": "BAJO",
      "rr": 1.63,
      "score": 77.2,
      "price": 139.91,
      "exposure_pct": 0.0,
      "open_risk_pct": 0.0,
      "drawdown_pct": 27.55,
      "operational_rule": false,
      "decision": "BLOCKED_BY_EXISTING_RULE"
    },
    {
      "id": "BLOCK-3",
      "date": "2026-07-17",
      "ticker": "DVN",
      "signal": "BUY",
      "reason": "Volumen relativo bajo",
      "risk": "BAJO",
      "rr": 1.63,
      "score": 74.9,
      "price": 43.71,
      "exposure_pct": 0.0,
      "open_risk_pct": 0.0,
      "drawdown_pct": 27.55,
      "operational_rule": false,
      "decision": "BLOCKED_BY_EXISTING_RULE"
    },
    {
      "id": "BLOCK-4",
      "date": "2026-07-17",
      "ticker": "NEE",
      "signal": "BUY",
      "reason": "Volumen relativo bajo",
      "risk": "BAJO",
      "rr": 1.63,
      "score": 74.2,
      "price": 88.86,
      "exposure_pct": 0.0,
      "open_risk_pct": 0.0,
      "drawdown_pct": 27.55,
      "operational_rule": false,
      "decision": "BLOCKED_BY_EXISTING_RULE"
    },
    {
      "id": "BLOCK-5",
      "date": "2026-07-17",
      "ticker": "HAL",
      "signal": "BUY",
      "reason": "Volumen relativo bajo",
      "risk": "BAJO",
      "rr": 1.63,
      "score": 70.7,
      "price": 35.19,
      "exposure_pct": 0.0,
      "open_risk_pct": 0.0,
      "drawdown_pct": 27.55,
      "operational_rule": false,
      "decision": "BLOCKED_BY_EXISTING_RULE"
    },
    {
      "id": "BLOCK-6",
      "date": "2026-07-17",
      "ticker": "KMI",
      "signal": "BUY",
      "reason": "Volumen relativo bajo",
      "risk": "BAJO",
      "rr": 1.62,
      "score": 67.3,
      "price": 32.22,
      "exposure_pct": 0.0,
      "open_risk_pct": 0.0,
      "drawdown_pct": 27.55,
      "operational_rule": false,
      "decision": "BLOCKED_BY_EXISTING_RULE"
    },
    {
      "id": "BLOCK-7",
      "date": "2026-07-17",
      "ticker": "UNH",
      "signal": "BUY",
      "reason": "Volumen relativo bajo",
      "risk": "BAJO",
      "rr": 1.63,
      "score": 78.9,
      "price": 434.5,
      "exposure_pct": 0.0,
      "open_risk_pct": 0.0,
      "drawdown_pct": 27.55,
      "operational_rule": false,
      "decision": "BLOCKED_BY_EXISTING_RULE"
    },
    {
      "id": "BLOCK-8",
      "date": "2026-07-17",
      "ticker": "PM",
      "signal": "BUY",
      "reason": "Volumen relativo bajo",
      "risk": "BAJO",
      "rr": 1.63,
      "score": 78.7,
      "price": 190.96,
      "exposure_pct": 0.0,
      "open_risk_pct": 0.0,
      "drawdown_pct": 27.55,
      "operational_rule": false,
      "decision": "BLOCKED_BY_EXISTING_RULE"
    },
    {
      "id": "BLOCK-9",
      "date": "2026-07-17",
      "ticker": "XYZ",
      "signal": "BUY",
      "reason": "Volumen relativo bajo",
      "risk": "BAJO",
      "rr": 1.63,
      "score": 78.2,
      "price": 80.5,
      "exposure_pct": 0.0,
      "open_risk_pct": 0.0,
      "drawdown_pct": 27.55,
      "operational_rule": false,
      "decision": "BLOCKED_BY_EXISTING_RULE"
    },
    {
      "id": "BLOCK-10",
      "date": "2026-07-17",
      "ticker": "NVO",
      "signal": "BUY",
      "reason": "Volumen relativo bajo",
      "risk": "BAJO",
      "rr": 1.64,
      "score": 77.8,
      "price": 50.46,
      "exposure_pct": 0.0,
      "open_risk_pct": 0.0,
      "drawdown_pct": 27.55,
      "operational_rule": false,
      "decision": "BLOCKED_BY_EXISTING_RULE"
    },
    {
      "id": "BLOCK-11",
      "date": "2026-07-17",
      "ticker": "DHR",
      "signal": "BUY",
      "reason": "Volumen relativo bajo",
      "risk": "BAJO",
      "rr": 1.63,
      "score": 77.5,
      "price": 203.14,
      "exposure_pct": 0.0,
      "open_risk_pct": 0.0,
      "drawdown_pct": 27.55,
      "operational_rule": false,
      "decision": "BLOCKED_BY_EXISTING_RULE"
    },
    {
      "id": "BLOCK-12",
      "date": "2026-07-17",
      "ticker": "TGT",
      "signal": "BUY",
      "reason": "Volumen relativo bajo",
      "risk": "BAJO",
      "rr": 1.63,
      "score": 77.5,
      "price": 138.91,
      "exposure_pct": 0.0,
      "open_risk_pct": 0.0,
      "drawdown_pct": 27.55,
      "operational_rule": false,
      "decision": "BLOCKED_BY_EXISTING_RULE"
    },
    {
      "id": "BLOCK-13",
      "date": "2026-07-17",
      "ticker": "GILD",
      "signal": "BUY",
      "reason": "Volumen relativo bajo",
      "risk": "BAJO",
      "rr": 1.63,
      "score": 77.4,
      "price": 134.6,
      "exposure_pct": 0.0,
      "open_risk_pct": 0.0,
      "drawdown_pct": 27.55,
      "operational_rule": false,
      "decision": "BLOCKED_BY_EXISTING_RULE"
    },
    {
      "id": "BLOCK-14",
      "date": "2026-07-17",
      "ticker": "ABBV",
      "signal": "BUY",
      "reason": "Volumen relativo bajo",
      "risk": "BAJO",
      "rr": 1.63,
      "score": 77.2,
      "price": 255.54,
      "exposure_pct": 0.0,
      "open_risk_pct": 0.0,
      "drawdown_pct": 27.55,
      "operational_rule": false,
      "decision": "BLOCKED_BY_EXISTING_RULE"
    },
    {
      "id": "BLOCK-15",
      "date": "2026-07-17",
      "ticker": "SCHD",
      "signal": "BUY",
      "reason": "Volumen relativo bajo",
      "risk": "BAJO",
      "rr": 1.63,
      "score": 76.7,
      "price": 32.85,
      "exposure_pct": 0.0,
      "open_risk_pct": 0.0,
      "drawdown_pct": 27.55,
      "operational_rule": false,
      "decision": "BLOCKED_BY_EXISTING_RULE"
    },
    {
      "id": "BLOCK-16",
      "date": "2026-07-17",
      "ticker": "AFL",
      "signal": "BUY",
      "reason": "Volumen relativo bajo",
      "risk": "BAJO",
      "rr": 1.63,
      "score": 76.5,
      "price": 124.15,
      "exposure_pct": 0.0,
      "open_risk_pct": 0.0,
      "drawdown_pct": 27.55,
      "operational_rule": false,
      "decision": "BLOCKED_BY_EXISTING_RULE"
    },
    {
      "id": "BLOCK-17",
      "date": "2026-07-17",
      "ticker": "MRK",
      "signal": "BUY",
      "reason": "Volumen relativo bajo",
      "risk": "BAJO",
      "rr": 1.63,
      "score": 76.0,
      "price": 127.38,
      "exposure_pct": 0.0,
      "open_risk_pct": 0.0,
      "drawdown_pct": 27.55,
      "operational_rule": false,
      "decision": "BLOCKED_BY_EXISTING_RULE"
    },
    {
      "id": "BLOCK-18",
      "date": "2026-07-17",
      "ticker": "TMO",
      "signal": "BUY",
      "reason": "Volumen relativo bajo",
      "risk": "BAJO",
      "rr": 1.63,
      "score": 75.8,
      "price": 532.78,
      "exposure_pct": 0.0,
      "open_risk_pct": 0.0,
      "drawdown_pct": 27.55,
      "operational_rule": false,
      "decision": "BLOCKED_BY_EXISTING_RULE"
    },
    {
      "id": "BLOCK-19",
      "date": "2026-07-17",
      "ticker": "F",
      "signal": "BUY",
      "reason": "Volumen relativo bajo",
      "risk": "BAJO",
      "rr": 1.62,
      "score": 75.8,
      "price": 14.39,
      "exposure_pct": 0.0,
      "open_risk_pct": 0.0,
      "drawdown_pct": 27.55,
      "operational_rule": false,
      "decision": "BLOCKED_BY_EXISTING_RULE"
    },
    {
      "id": "BLOCK-20",
      "date": "2026-07-17",
      "ticker": "XLRE",
      "signal": "BUY",
      "reason": "Volumen relativo bajo",
      "risk": "BAJO",
      "rr": 1.63,
      "score": 75.6,
      "price": 45.26,
      "exposure_pct": 0.0,
      "open_risk_pct": 0.0,
      "drawdown_pct": 27.55,
      "operational_rule": false,
      "decision": "BLOCKED_BY_EXISTING_RULE"
    },
    {
      "id": "BLOCK-21",
      "date": "2026-07-17",
      "ticker": "HMC",
      "signal": "BUY",
      "reason": "Volumen relativo bajo",
      "risk": "BAJO",
      "rr": 1.62,
      "score": 74.9,
      "price": 28.22,
      "exposure_pct": 0.0,
      "open_risk_pct": 0.0,
      "drawdown_pct": 27.55,
      "operational_rule": false,
      "decision": "BLOCKED_BY_EXISTING_RULE"
    },
    {
      "id": "BLOCK-22",
      "date": "2026-07-17",
      "ticker": "AXP",
      "signal": "BUY",
      "reason": "Volumen relativo bajo",
      "risk": "BAJO",
      "rr": 1.63,
      "score": 74.5,
      "price": 355.64,
      "exposure_pct": 0.0,
      "open_risk_pct": 0.0,
      "drawdown_pct": 27.55,
      "operational_rule": false,
      "decision": "BLOCKED_BY_EXISTING_RULE"
    },
    {
      "id": "BLOCK-23",
      "date": "2026-07-17",
      "ticker": "GS",
      "signal": "BUY",
      "reason": "Volumen relativo bajo",
      "risk": "BAJO",
      "rr": 1.63,
      "score": 72.6,
      "price": 1079.23,
      "exposure_pct": 0.0,
      "open_risk_pct": 0.0,
      "drawdown_pct": 27.55,
      "operational_rule": false,
      "decision": "BLOCKED_BY_EXISTING_RULE"
    },
    {
      "id": "BLOCK-24",
      "date": "2026-07-17",
      "ticker": "BKNG",
      "signal": "BUY",
      "reason": "Volumen relativo bajo",
      "risk": "BAJO",
      "rr": 1.63,
      "score": 72.4,
      "price": 181.52,
      "exposure_pct": 0.0,
      "open_risk_pct": 0.0,
      "drawdown_pct": 27.55,
      "operational_rule": false,
      "decision": "BLOCKED_BY_EXISTING_RULE"
    },
    {
      "id": "BLOCK-25",
      "date": "2026-07-17",
      "ticker": "XPEV",
      "signal": "BUY",
      "reason": "Volumen relativo bajo",
      "risk": "BAJO",
      "rr": 1.62,
      "score": 70.3,
      "price": 13.48,
      "exposure_pct": 0.0,
      "open_risk_pct": 0.0,
      "drawdown_pct": 27.55,
      "operational_rule": false,
      "decision": "BLOCKED_BY_EXISTING_RULE"
    },
    {
      "id": "BLOCK-26",
      "date": "2026-07-17",
      "ticker": "NU",
      "signal": "BUY",
      "reason": "Bloqueo operativo por drawdown máximo: 27.55%",
      "risk": "BAJO",
      "rr": 1.63,
      "score": 76.8,
      "price": 13.76,
      "exposure_pct": 0.0,
      "open_risk_pct": 0.0,
      "drawdown_pct": 27.55,
      "operational_rule": true,
      "decision": "BLOCKED_BY_OPERATIONAL_RULE"
    },
    {
      "id": "BLOCK-27",
      "date": "2026-07-17",
      "ticker": "XLP",
      "signal": "BUY",
      "reason": "Bloqueo operativo por drawdown máximo: 27.55%",
      "risk": "BAJO",
      "rr": 1.63,
      "score": 76.6,
      "price": 84.83,
      "exposure_pct": 0.0,
      "open_risk_pct": 0.0,
      "drawdown_pct": 27.55,
      "operational_rule": true,
      "decision": "BLOCKED_BY_OPERATIONAL_RULE"
    },
    {
      "id": "BLOCK-28",
      "date": "2026-07-17",
      "ticker": "SBUX",
      "signal": "BUY",
      "reason": "Volumen relativo bajo",
      "risk": "BAJO",
      "rr": 1.63,
      "score": 74.9,
      "price": 105.79,
      "exposure_pct": 0.0,
      "open_risk_pct": 0.0,
      "drawdown_pct": 27.55,
      "operational_rule": false,
      "decision": "BLOCKED_BY_EXISTING_RULE"
    },
    {
      "id": "BLOCK-29",
      "date": "2026-07-17",
      "ticker": "WFC",
      "signal": "BUY",
      "reason": "Volumen relativo bajo",
      "risk": "BAJO",
      "rr": 1.63,
      "score": 74.4,
      "price": 87.93,
      "exposure_pct": 0.0,
      "open_risk_pct": 0.0,
      "drawdown_pct": 27.55,
      "operational_rule": false,
      "decision": "BLOCKED_BY_EXISTING_RULE"
    },
    {
      "id": "BLOCK-30",
      "date": "2026-07-17",
      "ticker": "MDT",
      "signal": "BUY",
      "reason": "Volumen relativo bajo",
      "risk": "BAJO",
      "rr": 1.63,
      "score": 73.9,
      "price": 82.76,
      "exposure_pct": 0.0,
      "open_risk_pct": 0.0,
      "drawdown_pct": 27.55,
      "operational_rule": false,
      "decision": "BLOCKED_BY_EXISTING_RULE"
    },
    {
      "id": "BLOCK-31",
      "date": "2026-07-17",
      "ticker": "TDOC",
      "signal": "BUY",
      "reason": "Volumen relativo bajo",
      "risk": "BAJO",
      "rr": 1.62,
      "score": 73.1,
      "price": 9.37,
      "exposure_pct": 0.0,
      "open_risk_pct": 0.0,
      "drawdown_pct": 27.55,
      "operational_rule": false,
      "decision": "BLOCKED_BY_EXISTING_RULE"
    },
    {
      "id": "BLOCK-32",
      "date": "2026-07-17",
      "ticker": "XLV",
      "signal": "BUY",
      "reason": "Volumen relativo bajo",
      "risk": "BAJO",
      "rr": 1.63,
      "score": 73.0,
      "price": 161.0,
      "exposure_pct": 0.0,
      "open_risk_pct": 0.0,
      "drawdown_pct": 27.55,
      "operational_rule": false,
      "decision": "BLOCKED_BY_EXISTING_RULE"
    },
    {
      "id": "BLOCK-33",
      "date": "2026-07-17",
      "ticker": "AMGN",
      "signal": "BUY",
      "reason": "Volumen relativo bajo",
      "risk": "BAJO",
      "rr": 1.63,
      "score": 72.2,
      "price": 362.61,
      "exposure_pct": 0.0,
      "open_risk_pct": 0.0,
      "drawdown_pct": 27.55,
      "operational_rule": false,
      "decision": "BLOCKED_BY_EXISTING_RULE"
    },
    {
      "id": "BLOCK-34",
      "date": "2026-07-17",
      "ticker": "ABNB",
      "signal": "BUY",
      "reason": "Volumen relativo bajo",
      "risk": "BAJO",
      "rr": 1.63,
      "score": 71.7,
      "price": 146.56,
      "exposure_pct": 0.0,
      "open_risk_pct": 0.0,
      "drawdown_pct": 27.55,
      "operational_rule": false,
      "decision": "BLOCKED_BY_EXISTING_RULE"
    },
    {
      "id": "BLOCK-35",
      "date": "2026-07-17",
      "ticker": "CMG",
      "signal": "BUY",
      "reason": "Volumen relativo bajo",
      "risk": "BAJO",
      "rr": 1.63,
      "score": 71.5,
      "price": 34.39,
      "exposure_pct": 0.0,
      "open_risk_pct": 0.0,
      "drawdown_pct": 27.55,
      "operational_rule": false,
      "decision": "BLOCKED_BY_EXISTING_RULE"
    },
    {
      "id": "BLOCK-36",
      "date": "2026-07-17",
      "ticker": "IBB",
      "signal": "BUY",
      "reason": "Volumen relativo bajo",
      "risk": "BAJO",
      "rr": 1.63,
      "score": 71.3,
      "price": 189.49,
      "exposure_pct": 0.0,
      "open_risk_pct": 0.0,
      "drawdown_pct": 27.55,
      "operational_rule": false,
      "decision": "BLOCKED_BY_EXISTING_RULE"
    },
    {
      "id": "BLOCK-37",
      "date": "2026-07-17",
      "ticker": "HYG",
      "signal": "BUY",
      "reason": "Volumen relativo bajo",
      "risk": "BAJO",
      "rr": 1.63,
      "score": 70.6,
      "price": 79.74,
      "exposure_pct": 0.0,
      "open_risk_pct": 0.0,
      "drawdown_pct": 27.55,
      "operational_rule": false,
      "decision": "BLOCKED_BY_EXISTING_RULE"
    },
    {
      "id": "BLOCK-38",
      "date": "2026-07-17",
      "ticker": "SPY",
      "signal": "BUY",
      "reason": "Volumen relativo bajo",
      "risk": "BAJO",
      "rr": 1.63,
      "score": 69.7,
      "price": 745.12,
      "exposure_pct": 0.0,
      "open_risk_pct": 0.0,
      "drawdown_pct": 27.55,
      "operational_rule": false,
      "decision": "BLOCKED_BY_EXISTING_RULE"
    },
    {
      "id": "BLOCK-39",
      "date": "2026-07-17",
      "ticker": "VOO",
      "signal": "BUY",
      "reason": "Volumen relativo bajo",
      "risk": "BAJO",
      "rr": 1.63,
      "score": 68.4,
      "price": 684.89,
      "exposure_pct": 0.0,
      "open_risk_pct": 0.0,
      "drawdown_pct": 27.55,
      "operational_rule": false,
      "decision": "BLOCKED_BY_EXISTING_RULE"
    },
    {
      "id": "BLOCK-40",
      "date": "2026-07-17",
      "ticker": "PG",
      "signal": "BUY",
      "reason": "Volumen relativo bajo",
      "risk": "BAJO",
      "rr": 1.63,
      "score": 67.8,
      "price": 149.71,
      "exposure_pct": 0.0,
      "open_risk_pct": 0.0,
      "drawdown_pct": 27.55,
      "operational_rule": false,
      "decision": "BLOCKED_BY_EXISTING_RULE"
    },
    {
      "id": "BLOCK-41",
      "date": "2026-07-17",
      "ticker": "DIA",
      "signal": "BUY",
      "reason": "Bloqueo operativo por drawdown máximo: 27.55%",
      "risk": "BAJO",
      "rr": 1.63,
      "score": 68.2,
      "price": 522.1,
      "exposure_pct": 0.0,
      "open_risk_pct": 0.0,
      "drawdown_pct": 27.55,
      "operational_rule": true,
      "decision": "BLOCKED_BY_OPERATIONAL_RULE"
    },
    {
      "id": "BLOCK-42",
      "date": "2026-07-17",
      "ticker": "XBI",
      "signal": "BUY",
      "reason": "Volumen relativo bajo",
      "risk": "BAJO",
      "rr": 1.63,
      "score": 67.8,
      "price": 154.26,
      "exposure_pct": 0.0,
      "open_risk_pct": 0.0,
      "drawdown_pct": 27.55,
      "operational_rule": false,
      "decision": "BLOCKED_BY_EXISTING_RULE"
    },
    {
      "id": "BLOCK-43",
      "date": "2026-07-17",
      "ticker": "FIS",
      "signal": "BUY",
      "reason": "Volumen relativo bajo",
      "risk": "BAJO",
      "rr": 1.63,
      "score": 67.8,
      "price": 41.98,
      "exposure_pct": 0.0,
      "open_risk_pct": 0.0,
      "drawdown_pct": 27.55,
      "operational_rule": false,
      "decision": "BLOCKED_BY_EXISTING_RULE"
    },
    {
      "id": "BLOCK-44",
      "date": "2026-07-17",
      "ticker": "EXPE",
      "signal": "BUY",
      "reason": "Volumen relativo bajo",
      "risk": "BAJO",
      "rr": 1.63,
      "score": 67.1,
      "price": 267.98,
      "exposure_pct": 0.0,
      "open_risk_pct": 0.0,
      "drawdown_pct": 27.55,
      "operational_rule": false,
      "decision": "BLOCKED_BY_EXISTING_RULE"
    },
    {
      "id": "BLOCK-45",
      "date": "2026-07-17",
      "ticker": "FISV",
      "signal": "BUY",
      "reason": "Volumen relativo bajo",
      "risk": "BAJO",
      "rr": 1.63,
      "score": 66.8,
      "price": 50.89,
      "exposure_pct": 0.0,
      "open_risk_pct": 0.0,
      "drawdown_pct": 27.55,
      "operational_rule": false,
      "decision": "BLOCKED_BY_EXISTING_RULE"
    },
    {
      "id": "BLOCK-46",
      "date": "2026-07-17",
      "ticker": "XLC",
      "signal": "BUY",
      "reason": "Volumen relativo bajo",
      "risk": "BAJO",
      "rr": 1.63,
      "score": 66.5,
      "price": 110.41,
      "exposure_pct": 0.0,
      "open_risk_pct": 0.0,
      "drawdown_pct": 27.55,
      "operational_rule": false,
      "decision": "BLOCKED_BY_EXISTING_RULE"
    },
    {
      "id": "BLOCK-47",
      "date": "2026-07-17",
      "ticker": "SPOT",
      "signal": "BUY",
      "reason": "Volumen relativo bajo",
      "risk": "BAJO",
      "rr": 1.63,
      "score": 66.2,
      "price": 473.71,
      "exposure_pct": 0.0,
      "open_risk_pct": 0.0,
      "drawdown_pct": 27.55,
      "operational_rule": false,
      "decision": "BLOCKED_BY_EXISTING_RULE"
    },
    {
      "id": "BLOCK-48",
      "date": "2026-07-17",
      "ticker": "PFE",
      "signal": "BUY",
      "reason": "Volumen relativo bajo",
      "risk": "BAJO",
      "rr": 1.63,
      "score": 65.7,
      "price": 25.03,
      "exposure_pct": 0.0,
      "open_risk_pct": 0.0,
      "drawdown_pct": 27.55,
      "operational_rule": false,
      "decision": "BLOCKED_BY_EXISTING_RULE"
    },
    {
      "id": "BLOCK-49",
      "date": "2026-07-17",
      "ticker": "LULU",
      "signal": "BUY",
      "reason": "Volumen relativo bajo",
      "risk": "BAJO",
      "rr": 1.63,
      "score": 65.6,
      "price": 116.75,
      "exposure_pct": 0.0,
      "open_risk_pct": 0.0,
      "drawdown_pct": 27.55,
      "operational_rule": false,
      "decision": "BLOCKED_BY_EXISTING_RULE"
    },
    {
      "id": "BLOCK-50",
      "date": "2026-07-17",
      "ticker": "XLE",
      "signal": "BUY",
      "reason": "Volumen relativo bajo",
      "risk": "MEDIO",
      "rr": 1.63,
      "score": 74.3,
      "price": 57.53,
      "exposure_pct": 0.0,
      "open_risk_pct": 0.0,
      "drawdown_pct": 27.55,
      "operational_rule": false,
      "decision": "BLOCKED_BY_EXISTING_RULE"
    }
  ],
  "buy_candidates": [
    {
      "ticker": "OKE",
      "signal": "BUY",
      "score": 77.6,
      "risk": "BAJO",
      "already_open": false,
      "entry": "92.22 - 93.37",
      "stop": 89.94,
      "target": 98.06
    },
    {
      "ticker": "EOG",
      "signal": "BUY",
      "score": 77.2,
      "risk": "BAJO",
      "already_open": false,
      "entry": "138.67 - 140.44",
      "stop": 135.13,
      "target": 147.69
    },
    {
      "ticker": "DVN",
      "signal": "BUY",
      "score": 74.9,
      "risk": "BAJO",
      "already_open": false,
      "entry": "43.26 - 43.89",
      "stop": 42.0,
      "target": 46.48
    },
    {
      "ticker": "NEE",
      "signal": "BUY",
      "score": 74.2,
      "risk": "BAJO",
      "already_open": false,
      "entry": "88.33 - 89.1",
      "stop": 86.79,
      "target": 92.25
    },
    {
      "ticker": "HAL",
      "signal": "BUY",
      "score": 70.7,
      "risk": "BAJO",
      "already_open": false,
      "entry": "34.87 - 35.34",
      "stop": 33.93,
      "target": 37.26
    },
    {
      "ticker": "KMI",
      "signal": "BUY",
      "score": 67.3,
      "risk": "BAJO",
      "already_open": false,
      "entry": "31.98 - 32.32",
      "stop": 31.3,
      "target": 33.7
    },
    {
      "ticker": "UNH",
      "signal": "BUY",
      "score": 78.9,
      "risk": "BAJO",
      "already_open": false,
      "entry": "430.03 - 436.41",
      "stop": 417.27,
      "target": 462.58
    },
    {
      "ticker": "PM",
      "signal": "BUY",
      "score": 78.7,
      "risk": "BAJO",
      "already_open": false,
      "entry": "189.1 - 191.76",
      "stop": 183.77,
      "target": 202.68
    },
    {
      "ticker": "XYZ",
      "signal": "BUY",
      "score": 78.2,
      "risk": "BAJO",
      "already_open": false,
      "entry": "79.46 - 80.95",
      "stop": 76.49,
      "target": 87.03
    },
    {
      "ticker": "NVO",
      "signal": "BUY",
      "score": 77.8,
      "risk": "BAJO",
      "already_open": false,
      "entry": "50.02 - 50.64",
      "stop": 48.77,
      "target": 53.21
    },
    {
      "ticker": "DHR",
      "signal": "BUY",
      "score": 77.5,
      "risk": "BAJO",
      "already_open": false,
      "entry": "201.4 - 203.89",
      "stop": 196.41,
      "target": 214.1
    },
    {
      "ticker": "TGT",
      "signal": "BUY",
      "score": 77.5,
      "risk": "BAJO",
      "already_open": false,
      "entry": "137.42 - 139.56",
      "stop": 133.14,
      "target": 148.33
    },
    {
      "ticker": "GILD",
      "signal": "BUY",
      "score": 77.4,
      "risk": "BAJO",
      "already_open": false,
      "entry": "133.13 - 135.24",
      "stop": 128.9,
      "target": 143.91
    },
    {
      "ticker": "ABBV",
      "signal": "BUY",
      "score": 77.2,
      "risk": "BAJO",
      "already_open": false,
      "entry": "253.26 - 256.52",
      "stop": 246.73,
      "target": 269.89
    },
    {
      "ticker": "SCHD",
      "signal": "BUY",
      "score": 76.7,
      "risk": "BAJO",
      "already_open": false,
      "entry": "32.71 - 32.9",
      "stop": 32.32,
      "target": 33.7
    },
    {
      "ticker": "AFL",
      "signal": "BUY",
      "score": 76.5,
      "risk": "BAJO",
      "already_open": false,
      "entry": "123.38 - 124.49",
      "stop": 121.17,
      "target": 129.01
    },
    {
      "ticker": "MRK",
      "signal": "BUY",
      "score": 76.0,
      "risk": "BAJO",
      "already_open": false,
      "entry": "126.07 - 127.94",
      "stop": 122.33,
      "target": 135.61
    },
    {
      "ticker": "TMO",
      "signal": "BUY",
      "score": 75.8,
      "risk": "BAJO",
      "already_open": false,
      "entry": "528.08 - 534.79",
      "stop": 514.68,
      "target": 562.26
    },
    {
      "ticker": "F",
      "signal": "BUY",
      "score": 75.8,
      "risk": "BAJO",
      "already_open": false,
      "entry": "14.25 - 14.45",
      "stop": 13.83,
      "target": 15.3
    },
    {
      "ticker": "XLRE",
      "signal": "BUY",
      "score": 75.6,
      "risk": "BAJO",
      "already_open": false,
      "entry": "45.03 - 45.36",
      "stop": 44.39,
      "target": 46.68
    },
    {
      "ticker": "HMC",
      "signal": "BUY",
      "score": 74.9,
      "risk": "BAJO",
      "already_open": false,
      "entry": "27.98 - 28.32",
      "stop": 27.3,
      "target": 29.7
    },
    {
      "ticker": "AXP",
      "signal": "BUY",
      "score": 74.5,
      "risk": "BAJO",
      "already_open": false,
      "entry": "352.56 - 356.96",
      "stop": 343.76,
      "target": 375.01
    },
    {
      "ticker": "GS",
      "signal": "BUY",
      "score": 72.6,
      "risk": "BAJO",
      "already_open": false,
      "entry": "1066.57 - 1084.66",
      "stop": 1030.4,
      "target": 1158.8
    },
    {
      "ticker": "BKNG",
      "signal": "BUY",
      "score": 72.4,
      "risk": "BAJO",
      "already_open": false,
      "entry": "179.32 - 182.47",
      "stop": 173.03,
      "target": 195.37
    },
    {
      "ticker": "XPEV",
      "signal": "BUY",
      "score": 70.3,
      "risk": "BAJO",
      "already_open": false,
      "entry": "13.26 - 13.57",
      "stop": 12.64,
      "target": 14.83
    },
    {
      "ticker": "NU",
      "signal": "BUY",
      "score": 76.8,
      "risk": "BAJO",
      "already_open": false,
      "entry": "13.58 - 13.83",
      "stop": 13.09,
      "target": 14.84
    },
    {
      "ticker": "XLP",
      "signal": "BUY",
      "score": 76.6,
      "risk": "BAJO",
      "already_open": false,
      "entry": "84.31 - 85.05",
      "stop": 82.83,
      "target": 88.09
    },
    {
      "ticker": "SBUX",
      "signal": "BUY",
      "score": 74.9,
      "risk": "BAJO",
      "already_open": false,
      "entry": "104.78 - 106.22",
      "stop": 101.9,
      "target": 112.12
    },
    {
      "ticker": "WFC",
      "signal": "BUY",
      "score": 74.4,
      "risk": "BAJO",
      "already_open": false,
      "entry": "87.17 - 88.26",
      "stop": 84.99,
      "target": 92.73
    },
    {
      "ticker": "MDT",
      "signal": "BUY",
      "score": 73.9,
      "risk": "BAJO",
      "already_open": false,
      "entry": "81.86 - 83.15",
      "stop": 79.29,
      "target": 88.42
    },
    {
      "ticker": "TDOC",
      "signal": "BUY",
      "score": 73.1,
      "risk": "BAJO",
      "already_open": false,
      "entry": "9.22 - 9.44",
      "stop": 8.77,
      "target": 10.34
    },
    {
      "ticker": "XLV",
      "signal": "BUY",
      "score": 73.0,
      "risk": "BAJO",
      "already_open": false,
      "entry": "160.02 - 161.42",
      "stop": 157.22,
      "target": 167.16
    },
    {
      "ticker": "AMGN",
      "signal": "BUY",
      "score": 72.2,
      "risk": "BAJO",
      "already_open": false,
      "entry": "359.51 - 363.93",
      "stop": 350.67,
      "target": 382.06
    },
    {
      "ticker": "ABNB",
      "signal": "BUY",
      "score": 71.7,
      "risk": "BAJO",
      "already_open": false,
      "entry": "145.05 - 147.21",
      "stop": 140.73,
      "target": 156.05
    },
    {
      "ticker": "CMG",
      "signal": "BUY",
      "score": 71.5,
      "risk": "BAJO",
      "already_open": false,
      "entry": "33.94 - 34.58",
      "stop": 32.64,
      "target": 37.25
    },
    {
      "ticker": "IBB",
      "signal": "BUY",
      "score": 71.3,
      "risk": "BAJO",
      "already_open": false,
      "entry": "188.28 - 190.01",
      "stop": 184.82,
      "target": 197.1
    },
    {
      "ticker": "HYG",
      "signal": "BUY",
      "score": 70.6,
      "risk": "BAJO",
      "already_open": false,
      "entry": "79.68 - 79.77",
      "stop": 79.5,
      "target": 80.13
    },
    {
      "ticker": "SPY",
      "signal": "BUY",
      "score": 69.7,
      "risk": "BAJO",
      "already_open": false,
      "entry": "742.43 - 746.27",
      "stop": 734.74,
      "target": 762.04
    },
    {
      "ticker": "VOO",
      "signal": "BUY",
      "score": 68.4,
      "risk": "BAJO",
      "already_open": false,
      "entry": "682.44 - 685.94",
      "stop": 675.44,
      "target": 700.3
    },
    {
      "ticker": "PG",
      "signal": "BUY",
      "score": 67.8,
      "risk": "BAJO",
      "already_open": false,
      "entry": "148.5 - 150.23",
      "stop": 145.04,
      "target": 157.33
    },
    {
      "ticker": "DIA",
      "signal": "BUY",
      "score": 68.2,
      "risk": "BAJO",
      "already_open": false,
      "entry": "520.3 - 522.87",
      "stop": 515.16,
      "target": 533.42
    },
    {
      "ticker": "XBI",
      "signal": "BUY",
      "score": 67.8,
      "risk": "BAJO",
      "already_open": false,
      "entry": "152.76 - 154.9",
      "stop": 148.49,
      "target": 163.66
    },
    {
      "ticker": "FIS",
      "signal": "BUY",
      "score": 67.8,
      "risk": "BAJO",
      "already_open": false,
      "entry": "41.44 - 42.21",
      "stop": 39.91,
      "target": 45.36
    },
    {
      "ticker": "EXPE",
      "signal": "BUY",
      "score": 67.1,
      "risk": "BAJO",
      "already_open": false,
      "entry": "264.49 - 269.48",
      "stop": 254.51,
      "target": 289.94
    },
    {
      "ticker": "FISV",
      "signal": "BUY",
      "score": 66.8,
      "risk": "BAJO",
      "already_open": false,
      "entry": "50.14 - 51.21",
      "stop": 47.99,
      "target": 55.61
    },
    {
      "ticker": "XLC",
      "signal": "BUY",
      "score": 66.5,
      "risk": "BAJO",
      "already_open": false,
      "entry": "109.72 - 110.7",
      "stop": 107.77,
      "target": 114.72
    },
    {
      "ticker": "SPOT",
      "signal": "BUY",
      "score": 66.2,
      "risk": "BAJO",
      "already_open": false,
      "entry": "467.89 - 476.2",
      "stop": 451.27,
      "target": 510.28
    },
    {
      "ticker": "PFE",
      "signal": "BUY",
      "score": 65.7,
      "risk": "BAJO",
      "already_open": false,
      "entry": "24.85 - 25.11",
      "stop": 24.32,
      "target": 26.19
    },
    {
      "ticker": "LULU",
      "signal": "BUY",
      "score": 65.6,
      "risk": "BAJO",
      "already_open": false,
      "entry": "115.28 - 117.39",
      "stop": 111.07,
      "target": 126.02
    },
    {
      "ticker": "XLE",
      "signal": "BUY",
      "score": 74.3,
      "risk": "MEDIO",
      "already_open": false,
      "entry": "57.16 - 57.69",
      "stop": 56.09,
      "target": 59.87
    },
    {
      "ticker": "FANG",
      "signal": "BUY",
      "score": 72.3,
      "risk": "MEDIO",
      "already_open": false,
      "entry": "191.68 - 194.38",
      "stop": 186.29,
      "target": 205.43
    },
    {
      "ticker": "COP",
      "signal": "BUY",
      "score": 70.8,
      "risk": "MEDIO",
      "already_open": false,
      "entry": "112.96 - 114.3",
      "stop": 110.28,
      "target": 119.78
    },
    {
      "ticker": "OXY",
      "signal": "BUY",
      "score": 70.7,
      "risk": "MEDIO",
      "already_open": false,
      "entry": "54.11 - 54.9",
      "stop": 52.54,
      "target": 58.11
    },
    {
      "ticker": "LNG",
      "signal": "BUY",
      "score": 70.4,
      "risk": "MEDIO",
      "already_open": false,
      "entry": "258.49 - 262.07",
      "stop": 251.34,
      "target": 276.75
    },
    {
      "ticker": "ABT",
      "signal": "BUY",
      "score": 76.6,
      "risk": "MEDIO",
      "already_open": false,
      "entry": "98.43 - 100.07",
      "stop": 95.14,
      "target": 106.82
    },
    {
      "ticker": "BAC",
      "signal": "BUY",
      "score": 73.2,
      "risk": "MEDIO",
      "already_open": false,
      "entry": "60.97 - 61.6",
      "stop": 59.71,
      "target": 64.19
    },
    {
      "ticker": "V",
      "signal": "BUY",
      "score": 72.0,
      "risk": "MEDIO",
      "already_open": false,
      "entry": "354.93 - 359.48",
      "stop": 345.83,
      "target": 378.13
    },
    {
      "ticker": "MA",
      "signal": "BUY",
      "score": 70.5,
      "risk": "MEDIO",
      "already_open": false,
      "entry": "537.18 - 543.85",
      "stop": 523.85,
      "target": 571.19
    },
    {
      "ticker": "JPM",
      "signal": "BUY",
      "score": 70.2,
      "risk": "MEDIO",
      "already_open": false,
      "entry": "341.01 - 344.93",
      "stop": 333.17,
      "target": 361.01
    },
    {
      "ticker": "BX",
      "signal": "BUY",
      "score": 69.0,
      "risk": "MEDIO",
      "already_open": false,
      "entry": "126.15 - 128.09",
      "stop": 122.26,
      "target": 136.07
    },
    {
      "ticker": "GPN",
      "signal": "BUY",
      "score": 68.2,
      "risk": "MEDIO",
      "already_open": false,
      "entry": "77.72 - 79.25",
      "stop": 74.68,
      "target": 85.49
    },
    {
      "ticker": "REGN",
      "signal": "BUY",
      "score": 64.8,
      "risk": "MEDIO",
      "already_open": false,
      "entry": "668.36 - 676.55",
      "stop": 651.98,
      "target": 710.12
    }
  ],
  "notes": [
    "Este archivo no crea lógica nueva; resume bloqueos ya existentes en historial_senales.json.",
    "Sirve para explicar por qué el bot no abrió compras aunque hubiera señales BUY."
  ]
}